notrandom.py
notrandom-1.0.0.dist-info/METADATA
notrandom-1.0.0.dist-info/WHEEL
notrandom-1.0.0.dist-info/top_level.txt
notrandom-1.0.0.dist-info/RECORD
