Metadata-Version: 2.1
Name: notrandom
Version: 1.0.0
Summary: Pseudorandom, 100% reproducible variable generators
Author-email: Alon Krymgand <os@alon.kr>
Keywords: random,pseudorandom,generators
Requires-Python: >=3.7
